roboboards/__init__.py
roboboards/roboboards.py
robo_boards-0.1.1b0.dist-info/LICENSE
robo_boards-0.1.1b0.dist-info/METADATA
robo_boards-0.1.1b0.dist-info/WHEEL
robo_boards-0.1.1b0.dist-info/top_level.txt
robo_boards-0.1.1b0.dist-info/RECORD
