Metadata-Version: 2.1
Name: robo-boards
Version: 0.1.1b0
Summary: interface modules for microprocessor boards
Home-page: https://github.com/mkner/robo-boards
Author: Mike Knerr
License: BSD
Keywords: mobile robotics,microprocessor boards,arduino,ML298P
Platform: UNKNOWN
Classifier: Programming Language :: Python :: 3
Classifier: License :: OSI Approved :: BSD License
Classifier: Operating System :: OS Independent
License-File: LICENSE
